Workbook
Name Currency: 'Dish Input'!$F$3

Sheet Dashboard
E1: DISH PROFITABILITY TRACKER
B2: Dish Profitability Tracker | E2: Point Numera — pointnumera.com
B3: 📊 Dashboard | E3: [ Point Numera Logo ]
B4: 🍽️ Dish Input
B5: 📝 Notes
E6: TARGET FOOD COST %
E7: Target Food Cost % | F7: 0.3
E9: DISH SUMMARY
E10: Dish Name | F10: ="Selling Price ("&'Dish Input'!$F$3&")" -> Selling Price (CHF) | G10: Food Cost % | H10: ="Gross Margin ("&'Dish Input'!$F$3&")" -> Gross Margin (CHF) | I10: Gross Margin % | J10: Status
E11: ='Dish Input'!F7 -> Grilled Salmon Bowl | F11: ='Dish Input'!F10 -> 22.889908 | G11: ='Dish Input'!J27 -> 0.20205411 | H11: ='Dish Input'!J28 -> 18.264908 | I11: ='Dish Input'!J29 -> 0.79794589 | J11: =IF(F11=0,"—",IF(G11<=$F$7,"✅ On Target",IF(G11<=$F$7+0.05,"⚠ Watch","❌ Over"))) -> ✅ On Target
E12: ='Dish Input'!F33 -> Margherita Pizza | F12: ='Dish Input'!F36 -> 15.137615 | G12: ='Dish Input'!J53 -> 0.20373091 | H12: ='Dish Input'!J54 -> 12.053615 | I12: ='Dish Input'!J55 -> 0.79626909 | J12: =IF(F12=0,"—",IF(G12<=$F$7,"✅ On Target",IF(G12<=$F$7+0.05,"⚠ Watch","❌ Over"))) -> ✅ On Target
E13: ='Dish Input'!F59 -> Dish 3 | F13: ='Dish Input'!F62 -> 0 | G13: ='Dish Input'!J79 -> 0 | H13: ='Dish Input'!J80 -> 0 | I13: ='Dish Input'!J81 -> 0 | J13: =IF(F13=0,"—",IF(G13<=$F$7,"✅ On Target",IF(G13<=$F$7+0.05,"⚠ Watch","❌ Over"))) -> —
E14: ='Dish Input'!F85 -> Dish 4 | F14: ='Dish Input'!F88 -> 0 | G14: ='Dish Input'!J105 -> 0 | H14: ='Dish Input'!J106 -> 0 | I14: ='Dish Input'!J107 -> 0 | J14: =IF(F14=0,"—",IF(G14<=$F$7,"✅ On Target",IF(G14<=$F$7+0.05,"⚠ Watch","❌ Over"))) -> —
E15: ='Dish Input'!F111 -> Dish 5 | F15: ='Dish Input'!F114 -> 0 | G15: ='Dish Input'!J131 -> 0 | H15: ='Dish Input'!J132 -> 0 | I15: ='Dish Input'!J133 -> 0 | J15: =IF(F15=0,"—",IF(G15<=$F$7,"✅ On Target",IF(G15<=$F$7+0.05,"⚠ Watch","❌ Over"))) -> —
E17: AVERAGES | F17: Avg Food Cost %: | G17: =IFERROR(AVERAGEIF(F11:F15,">0",G11:G15),0) -> 0.20289251 | H17: Avg Gross Margin %: | I17: =IFERROR(AVERAGEIF(F11:F15,">0",I11:I15),0) -> 0.79710749
E19: COST vs MARGIN BREAKDOWN
E20: Avg Food Cost % | F20: Avg Gross Margin %
E21: =G17 -> 0.20289251 | F21: =I17 -> 0.79710749
E23: PRICE COMPOSITION
E24: Select Dish: | F24: Grilled Salmon Bowl | G24: =IFERROR(MATCH(F24,$E$11:$E$15,0),1) -> 1
E25: Component | F25: % of Selling Price | G25: ="Cost ("&'Dish Input'!$F$3&")" -> Cost (CHF)
E26: =IFERROR(IF(CHOOSE($G$24,'Dish Input'!E13,'Dish Input'!E39,'Dish Input'!E65,'Dish Input'!E91,'Dish Input'!E117)=0,"",CHOOSE($G$24,'Dish Input'!E13,'Dish Input'!E39,'Dish Input'!E65,'Dish Input'!E91,'Dish Input'!E117)),"") -> Salmon fillet | F26: =IF(E26="","",IFERROR(CHOOSE($G$24,'Dish Input'!J13,'Dish Input'!J39,'Dish Input'!J65,'Dish Input'!J91,'Dish Input'!J117)/CHOOSE($G$24,'Dish Input'!F10,'Dish Input'!F36,'Dish Input'!F62,'Dish Input'!F88,'Dish Input'!F114),0)) -> 0.078637275 | G26: =IF(E26="","",IFERROR(CHOOSE($G$24,'Dish Input'!J13,'Dish Input'!J39,'Dish Input'!J65,'Dish Input'!J91,'Dish Input'!J117),0)) -> 1.8
E27: =IFERROR(IF(CHOOSE($G$24,'Dish Input'!E14,'Dish Input'!E40,'Dish Input'!E66,'Dish Input'!E92,'Dish Input'!E118)=0,"",CHOOSE($G$24,'Dish Input'!E14,'Dish Input'!E40,'Dish Input'!E66,'Dish Input'!E92,'Dish Input'!E118)),"") -> Basmati rice | F27: =IF(E27="","",IFERROR(CHOOSE($G$24,'Dish Input'!J14,'Dish Input'!J40,'Dish Input'!J66,'Dish Input'!J92,'Dish Input'!J118)/CHOOSE($G$24,'Dish Input'!F10,'Dish Input'!F36,'Dish Input'!F62,'Dish Input'!F88,'Dish Input'!F114),0)) -> 0.015727455 | G27: =IF(E27="","",IFERROR(CHOOSE($G$24,'Dish Input'!J14,'Dish Input'!J40,'Dish Input'!J66,'Dish Input'!J92,'Dish Input'!J118),0)) -> 0.36
E28: =IFERROR(IF(CHOOSE($G$24,'Dish Input'!E15,'Dish Input'!E41,'Dish Input'!E67,'Dish Input'!E93,'Dish Input'!E119)=0,"",CHOOSE($G$24,'Dish Input'!E15,'Dish Input'!E41,'Dish Input'!E67,'Dish Input'!E93,'Dish Input'!E119)),"") -> Avocado | F28: =IF(E28="","",IFERROR(CHOOSE($G$24,'Dish Input'!J15,'Dish Input'!J41,'Dish Input'!J67,'Dish Input'!J93,'Dish Input'!J119)/CHOOSE($G$24,'Dish Input'!F10,'Dish Input'!F36,'Dish Input'!F62,'Dish Input'!F88,'Dish Input'!F114),0)) -> 0.05242485 | G28: =IF(E28="","",IFERROR(CHOOSE($G$24,'Dish Input'!J15,'Dish Input'!J41,'Dish Input'!J67,'Dish Input'!J93,'Dish Input'!J119),0)) -> 1.2
E29: =IFERROR(IF(CHOOSE($G$24,'Dish Input'!E16,'Dish Input'!E42,'Dish Input'!E68,'Dish Input'!E94,'Dish Input'!E120)=0,"",CHOOSE($G$24,'Dish Input'!E16,'Dish Input'!E42,'Dish Input'!E68,'Dish Input'!E94,'Dish Input'!E120)),"") -> Edamame | F29: =IF(E29="","",IFERROR(CHOOSE($G$24,'Dish Input'!J16,'Dish Input'!J42,'Dish Input'!J68,'Dish Input'!J94,'Dish Input'!J120)/CHOOSE($G$24,'Dish Input'!F10,'Dish Input'!F36,'Dish Input'!F62,'Dish Input'!F88,'Dish Input'!F114),0)) -> 0.01747495 | G29: =IF(E29="","",IFERROR(CHOOSE($G$24,'Dish Input'!J16,'Dish Input'!J42,'Dish Input'!J68,'Dish Input'!J94,'Dish Input'!J120),0)) -> 0.4
E30: =IFERROR(IF(CHOOSE($G$24,'Dish Input'!E17,'Dish Input'!E43,'Dish Input'!E69,'Dish Input'!E95,'Dish Input'!E121)=0,"",CHOOSE($G$24,'Dish Input'!E17,'Dish Input'!E43,'Dish Input'!E69,'Dish Input'!E95,'Dish Input'!E121)),"") -> Sesame dressing | F30: =IF(E30="","",IFERROR(CHOOSE($G$24,'Dish Input'!J17,'Dish Input'!J43,'Dish Input'!J69,'Dish Input'!J95,'Dish Input'!J121)/CHOOSE($G$24,'Dish Input'!F10,'Dish Input'!F36,'Dish Input'!F62,'Dish Input'!F88,'Dish Input'!F114),0)) -> 0.015727455 | G30: =IF(E30="","",IFERROR(CHOOSE($G$24,'Dish Input'!J17,'Dish Input'!J43,'Dish Input'!J69,'Dish Input'!J95,'Dish Input'!J121),0)) -> 0.36
E31: =IFERROR(IF(CHOOSE($G$24,'Dish Input'!E18,'Dish Input'!E44,'Dish Input'!E70,'Dish Input'!E96,'Dish Input'!E122)=0,"",CHOOSE($G$24,'Dish Input'!E18,'Dish Input'!E44,'Dish Input'!E70,'Dish Input'!E96,'Dish Input'!E122)),"") -> Spring onion | F31: =IF(E31="","",IFERROR(CHOOSE($G$24,'Dish Input'!J18,'Dish Input'!J44,'Dish Input'!J70,'Dish Input'!J96,'Dish Input'!J122)/CHOOSE($G$24,'Dish Input'!F10,'Dish Input'!F36,'Dish Input'!F62,'Dish Input'!F88,'Dish Input'!F114),0)) -> 0.0021843687 | G31: =IF(E31="","",IFERROR(CHOOSE($G$24,'Dish Input'!J18,'Dish Input'!J44,'Dish Input'!J70,'Dish Input'!J96,'Dish Input'!J122),0)) -> 0.05
E32: =IFERROR(IF(CHOOSE($G$24,'Dish Input'!E19,'Dish Input'!E45,'Dish Input'!E71,'Dish Input'!E97,'Dish Input'!E123)=0,"",CHOOSE($G$24,'Dish Input'!E19,'Dish Input'!E45,'Dish Input'!E71,'Dish Input'!E97,'Dish Input'!E123)),"") -> Sesame seeds | F32: =IF(E32="","",IFERROR(CHOOSE($G$24,'Dish Input'!J19,'Dish Input'!J45,'Dish Input'!J71,'Dish Input'!J97,'Dish Input'!J123)/CHOOSE($G$24,'Dish Input'!F10,'Dish Input'!F36,'Dish Input'!F62,'Dish Input'!F88,'Dish Input'!F114),0)) -> 0.0054609218 | G32: =IF(E32="","",IFERROR(CHOOSE($G$24,'Dish Input'!J19,'Dish Input'!J45,'Dish Input'!J71,'Dish Input'!J97,'Dish Input'!J123),0)) -> 0.125
E33: =IFERROR(IF(CHOOSE($G$24,'Dish Input'!E20,'Dish Input'!E46,'Dish Input'!E72,'Dish Input'!E98,'Dish Input'!E124)=0,"",CHOOSE($G$24,'Dish Input'!E20,'Dish Input'!E46,'Dish Input'!E72,'Dish Input'!E98,'Dish Input'!E124)),"") -> Lime wedge | F33: =IF(E33="","",IFERROR(CHOOSE($G$24,'Dish Input'!J20,'Dish Input'!J46,'Dish Input'!J72,'Dish Input'!J98,'Dish Input'!J124)/CHOOSE($G$24,'Dish Input'!F10,'Dish Input'!F36,'Dish Input'!F62,'Dish Input'!F88,'Dish Input'!F114),0)) -> 0.0065531062 | G33: =IF(E33="","",IFERROR(CHOOSE($G$24,'Dish Input'!J20,'Dish Input'!J46,'Dish Input'!J72,'Dish Input'!J98,'Dish Input'!J124),0)) -> 0.15
E34: =IFERROR(IF(CHOOSE($G$24,'Dish Input'!E21,'Dish Input'!E47,'Dish Input'!E73,'Dish Input'!E99,'Dish Input'!E125)=0,"",CHOOSE($G$24,'Dish Input'!E21,'Dish Input'!E47,'Dish Input'!E73,'Dish Input'!E99,'Dish Input'!E125)),"") -> Soy sauce | F34: =IF(E34="","",IFERROR(CHOOSE($G$24,'Dish Input'!J21,'Dish Input'!J47,'Dish Input'!J73,'Dish Input'!J99,'Dish Input'!J125)/CHOOSE($G$24,'Dish Input'!F10,'Dish Input'!F36,'Dish Input'!F62,'Dish Input'!F88,'Dish Input'!F114),0)) -> 0.0026212425 | G34: =IF(E34="","",IFERROR(CHOOSE($G$24,'Dish Input'!J21,'Dish Input'!J47,'Dish Input'!J73,'Dish Input'!J99,'Dish Input'!J125),0)) -> 0.06
E35: =IFERROR(IF(CHOOSE($G$24,'Dish Input'!E22,'Dish Input'!E48,'Dish Input'!E74,'Dish Input'!E100,'Dish Input'!E126)=0,"",CHOOSE($G$24,'Dish Input'!E22,'Dish Input'!E48,'Dish Input'!E74,'Dish Input'!E100,'Dish Input'!E126)),"") -> Pickled ginger | F35: =IF(E35="","",IFERROR(CHOOSE($G$24,'Dish Input'!J22,'Dish Input'!J48,'Dish Input'!J74,'Dish Input'!J100,'Dish Input'!J126)/CHOOSE($G$24,'Dish Input'!F10,'Dish Input'!F36,'Dish Input'!F62,'Dish Input'!F88,'Dish Input'!F114),0)) -> 0.005242485 | G35: =IF(E35="","",IFERROR(CHOOSE($G$24,'Dish Input'!J22,'Dish Input'!J48,'Dish Input'!J74,'Dish Input'!J100,'Dish Input'!J126),0)) -> 0.12
E36: =IFERROR(IF(CHOOSE($G$24,'Dish Input'!E23,'Dish Input'!E49,'Dish Input'!E75,'Dish Input'!E101,'Dish Input'!E127)=0,"",CHOOSE($G$24,'Dish Input'!E23,'Dish Input'!E49,'Dish Input'!E75,'Dish Input'!E101,'Dish Input'!E127)),"") | F36: =IF(E36="","",IFERROR(CHOOSE($G$24,'Dish Input'!J23,'Dish Input'!J49,'Dish Input'!J75,'Dish Input'!J101,'Dish Input'!J127)/CHOOSE($G$24,'Dish Input'!F10,'Dish Input'!F36,'Dish Input'!F62,'Dish Input'!F88,'Dish Input'!F114),0)) | G36: =IF(E36="","",IFERROR(CHOOSE($G$24,'Dish Input'!J23,'Dish Input'!J49,'Dish Input'!J75,'Dish Input'!J101,'Dish Input'!J127),0))
E37: =IFERROR(IF(CHOOSE($G$24,'Dish Input'!E24,'Dish Input'!E50,'Dish Input'!E76,'Dish Input'!E102,'Dish Input'!E128)=0,"",CHOOSE($G$24,'Dish Input'!E24,'Dish Input'!E50,'Dish Input'!E76,'Dish Input'!E102,'Dish Input'!E128)),"") | F37: =IF(E37="","",IFERROR(CHOOSE($G$24,'Dish Input'!J24,'Dish Input'!J50,'Dish Input'!J76,'Dish Input'!J102,'Dish Input'!J128)/CHOOSE($G$24,'Dish Input'!F10,'Dish Input'!F36,'Dish Input'!F62,'Dish Input'!F88,'Dish Input'!F114),0)) | G37: =IF(E37="","",IFERROR(CHOOSE($G$24,'Dish Input'!J24,'Dish Input'!J50,'Dish Input'!J76,'Dish Input'!J102,'Dish Input'!J128),0))
E38: Gross Margin | F38: =IFERROR(CHOOSE($G$24,'Dish Input'!J28,'Dish Input'!J54,'Dish Input'!J80,'Dish Input'!J106,'Dish Input'!J132)/CHOOSE($G$24,'Dish Input'!F10,'Dish Input'!F36,'Dish Input'!F62,'Dish Input'!F88,'Dish Input'!F114),0) -> 0.79794589 | G38: =IFERROR(CHOOSE($G$24,'Dish Input'!J28,'Dish Input'!J54,'Dish Input'!J80,'Dish Input'!J106,'Dish Input'!J132),0) -> 18.264908

Sheet Dish Input
E1: DISH INPUT
B2: Dish Profitability Tracker | E2: Enter dish details and ingredients. Blue values are editable
B3: 📊 Dashboard | E3: Currency: | F3: CHF
B4: 🍽️ Dish Input
B5: 📝 Notes
E6: DISH 1
E7: Dish Name | F7: Grilled Salmon Bowl
E8: Selling Price (incl. VAT) | F8: 24.95
E9: VAT Rate % | F9: 0.09
E10: Price excl. VAT | F10: =IFERROR(F8/(1+F9),0) -> 22.889908
E12: Ingredient | F12: Qty | G12: Unit | H12: ="Cost / Bulk ("&$F$3&")" -> Cost / Bulk (CHF) | I12: Bulk Unit | J12: ="Cost / Portion ("&$F$3&")" -> Cost / Portion (CHF)
E13: Salmon fillet | F13: 180 | G13: g | H13: 10 | I13: =IF(G13="","",IF(G13="g","per kg",IF(G13="ml","per L",IF(G13="oz","per lb",IF(G13="kg","per kg",IF(G13="L","per L",IF(G13="lb","per lb",IF(G13="fl oz","per fl oz","per unit")))))))) -> per kg | J13: =IF(F13="","",IF(OR(G13="g",G13="ml"),H13/1000*F13,IF(G13="oz",H13/16*F13,H13*F13))) -> 1.8
E14: Basmati rice | F14: 120 | G14: g | H14: 3 | I14: =IF(G14="","",IF(G14="g","per kg",IF(G14="ml","per L",IF(G14="oz","per lb",IF(G14="kg","per kg",IF(G14="L","per L",IF(G14="lb","per lb",IF(G14="fl oz","per fl oz","per unit")))))))) -> per kg | J14: =IF(F14="","",IF(OR(G14="g",G14="ml"),H14/1000*F14,IF(G14="oz",H14/16*F14,H14*F14))) -> 0.36
E15: Avocado | F15: 80 | G15: g | H15: 15 | I15: =IF(G15="","",IF(G15="g","per kg",IF(G15="ml","per L",IF(G15="oz","per lb",IF(G15="kg","per kg",IF(G15="L","per L",IF(G15="lb","per lb",IF(G15="fl oz","per fl oz","per unit")))))))) -> per kg | J15: =IF(F15="","",IF(OR(G15="g",G15="ml"),H15/1000*F15,IF(G15="oz",H15/16*F15,H15*F15))) -> 1.2
E16: Edamame | F16: 50 | G16: g | H16: 8 | I16: =IF(G16="","",IF(G16="g","per kg",IF(G16="ml","per L",IF(G16="oz","per lb",IF(G16="kg","per kg",IF(G16="L","per L",IF(G16="lb","per lb",IF(G16="fl oz","per fl oz","per unit")))))))) -> per kg | J16: =IF(F16="","",IF(OR(G16="g",G16="ml"),H16/1000*F16,IF(G16="oz",H16/16*F16,H16*F16))) -> 0.4
E17: Sesame dressing | F17: 30 | G17: ml | H17: 12 | I17: =IF(G17="","",IF(G17="g","per kg",IF(G17="ml","per L",IF(G17="oz","per lb",IF(G17="kg","per kg",IF(G17="L","per L",IF(G17="lb","per lb",IF(G17="fl oz","per fl oz","per unit")))))))) -> per L | J17: =IF(F17="","",IF(OR(G17="g",G17="ml"),H17/1000*F17,IF(G17="oz",H17/16*F17,H17*F17))) -> 0.36
E18: Spring onion | F18: 10 | G18: g | H18: 5 | I18: =IF(G18="","",IF(G18="g","per kg",IF(G18="ml","per L",IF(G18="oz","per lb",IF(G18="kg","per kg",IF(G18="L","per L",IF(G18="lb","per lb",IF(G18="fl oz","per fl oz","per unit")))))))) -> per kg | J18: =IF(F18="","",IF(OR(G18="g",G18="ml"),H18/1000*F18,IF(G18="oz",H18/16*F18,H18*F18))) -> 0.05
E19: Sesame seeds | F19: 5 | G19: g | H19: 25 | I19: =IF(G19="","",IF(G19="g","per kg",IF(G19="ml","per L",IF(G19="oz","per lb",IF(G19="kg","per kg",IF(G19="L","per L",IF(G19="lb","per lb",IF(G19="fl oz","per fl oz","per unit")))))))) -> per kg | J19: =IF(F19="","",IF(OR(G19="g",G19="ml"),H19/1000*F19,IF(G19="oz",H19/16*F19,H19*F19))) -> 0.125
E20: Lime wedge | F20: 1 | G20: pcs | H20: 0.15 | I20: =IF(G20="","",IF(G20="g","per kg",IF(G20="ml","per L",IF(G20="oz","per lb",IF(G20="kg","per kg",IF(G20="L","per L",IF(G20="lb","per lb",IF(G20="fl oz","per fl oz","per unit")))))))) -> per unit | J20: =IF(F20="","",IF(OR(G20="g",G20="ml"),H20/1000*F20,IF(G20="oz",H20/16*F20,H20*F20))) -> 0.15
E21: Soy sauce | F21: 15 | G21: ml | H21: 4 | I21: =IF(G21="","",IF(G21="g","per kg",IF(G21="ml","per L",IF(G21="oz","per lb",IF(G21="kg","per kg",IF(G21="L","per L",IF(G21="lb","per lb",IF(G21="fl oz","per fl oz","per unit")))))))) -> per L | J21: =IF(F21="","",IF(OR(G21="g",G21="ml"),H21/1000*F21,IF(G21="oz",H21/16*F21,H21*F21))) -> 0.06
E22: Pickled ginger | F22: 10 | G22: g | H22: 12 | I22: =IF(G22="","",IF(G22="g","per kg",IF(G22="ml","per L",IF(G22="oz","per lb",IF(G22="kg","per kg",IF(G22="L","per L",IF(G22="lb","per lb",IF(G22="fl oz","per fl oz","per unit")))))))) -> per kg | J22: =IF(F22="","",IF(OR(G22="g",G22="ml"),H22/1000*F22,IF(G22="oz",H22/16*F22,H22*F22))) -> 0.12
I23: =IF(G23="","",IF(G23="g","per kg",IF(G23="ml","per L",IF(G23="oz","per lb",IF(G23="kg","per kg",IF(G23="L","per L",IF(G23="lb","per lb",IF(G23="fl oz","per fl oz","per unit")))))))) | J23: =IF(F23="","",IF(OR(G23="g",G23="ml"),H23/1000*F23,IF(G23="oz",H23/16*F23,H23*F23)))
I24: =IF(G24="","",IF(G24="g","per kg",IF(G24="ml","per L",IF(G24="oz","per lb",IF(G24="kg","per kg",IF(G24="L","per L",IF(G24="lb","per lb",IF(G24="fl oz","per fl oz","per unit")))))))) | J24: =IF(F24="","",IF(OR(G24="g",G24="ml"),H24/1000*F24,IF(G24="oz",H24/16*F24,H24*F24)))
E26: Total Ingredient Cost | J26: =SUM(J13:J24) -> 4.625
E27: Food Cost % | J27: =IFERROR(J26/F10,0) -> 0.20205411
E28: Gross Margin | J28: =F10-J26 -> 18.264908
E29: Gross Margin % | J29: =IFERROR(J28/F10,0) -> 0.79794589
E30: Biggest Cost Driver | J30: =IFERROR(INDEX(E13:E24,MATCH(MAX(J13:J24),J13:J24,0)),"-") -> Salmon fillet
E31: Target Food Cost % | J31: =Dashboard!F7 -> 0.3
E32: DISH 2
E33: Dish Name | F33: Margherita Pizza
E34: Selling Price (incl. VAT) | F34: 16.5
E35: VAT Rate % | F35: 0.09
E36: Price excl. VAT | F36: =IFERROR(F34/(1+F35),0) -> 15.137615
E38: Ingredient | F38: Qty | G38: Unit | H38: ="Cost / Bulk ("&$F$3&")" -> Cost / Bulk (CHF) | I38: Bulk Unit | J38: ="Cost / Portion ("&$F$3&")" -> Cost / Portion (CHF)
E39: Pizza dough | F39: 250 | G39: g | H39: 2 | I39: =IF(G39="","",IF(G39="g","per kg",IF(G39="ml","per L",IF(G39="oz","per lb",IF(G39="kg","per kg",IF(G39="L","per L",IF(G39="lb","per lb",IF(G39="fl oz","per fl oz","per unit")))))))) -> per kg | J39: =IF(F39="","",IF(OR(G39="g",G39="ml"),H39/1000*F39,IF(G39="oz",H39/16*F39,H39*F39))) -> 0.5
E40: Mozzarella | F40: 125 | G40: g | H40: 12 | I40: =IF(G40="","",IF(G40="g","per kg",IF(G40="ml","per L",IF(G40="oz","per lb",IF(G40="kg","per kg",IF(G40="L","per L",IF(G40="lb","per lb",IF(G40="fl oz","per fl oz","per unit")))))))) -> per kg | J40: =IF(F40="","",IF(OR(G40="g",G40="ml"),H40/1000*F40,IF(G40="oz",H40/16*F40,H40*F40))) -> 1.5
E41: Tomato sauce | F41: 80 | G41: ml | H41: 5 | I41: =IF(G41="","",IF(G41="g","per kg",IF(G41="ml","per L",IF(G41="oz","per lb",IF(G41="kg","per kg",IF(G41="L","per L",IF(G41="lb","per lb",IF(G41="fl oz","per fl oz","per unit")))))))) -> per L | J41: =IF(F41="","",IF(OR(G41="g",G41="ml"),H41/1000*F41,IF(G41="oz",H41/16*F41,H41*F41))) -> 0.4
E42: Fresh basil | F42: 5 | G42: g | H42: 30 | I42: =IF(G42="","",IF(G42="g","per kg",IF(G42="ml","per L",IF(G42="oz","per lb",IF(G42="kg","per kg",IF(G42="L","per L",IF(G42="lb","per lb",IF(G42="fl oz","per fl oz","per unit")))))))) -> per kg | J42: =IF(F42="","",IF(OR(G42="g",G42="ml"),H42/1000*F42,IF(G42="oz",H42/16*F42,H42*F42))) -> 0.15
E43: Olive oil | F43: 15 | G43: ml | H43: 10 | I43: =IF(G43="","",IF(G43="g","per kg",IF(G43="ml","per L",IF(G43="oz","per lb",IF(G43="kg","per kg",IF(G43="L","per L",IF(G43="lb","per lb",IF(G43="fl oz","per fl oz","per unit")))))))) -> per L | J43: =IF(F43="","",IF(OR(G43="g",G43="ml"),H43/1000*F43,IF(G43="oz",H43/16*F43,H43*F43))) -> 0.15
E44: Parmesan | F44: 15 | G44: g | H44: 25 | I44: =IF(G44="","",IF(G44="g","per kg",IF(G44="ml","per L",IF(G44="oz","per lb",IF(G44="kg","per kg",IF(G44="L","per L",IF(G44="lb","per lb",IF(G44="fl oz","per fl oz","per unit")))))))) -> per kg | J44: =IF(F44="","",IF(OR(G44="g",G44="ml"),H44/1000*F44,IF(G44="oz",H44/16*F44,H44*F44))) -> 0.375
E45: Sea salt | F45: 3 | G45: g | H45: 3 | I45: =IF(G45="","",IF(G45="g","per kg",IF(G45="ml","per L",IF(G45="oz","per lb",IF(G45="kg","per kg",IF(G45="L","per L",IF(G45="lb","per lb",IF(G45="fl oz","per fl oz","per unit")))))))) -> per kg | J45: =IF(F45="","",IF(OR(G45="g",G45="ml"),H45/1000*F45,IF(G45="oz",H45/16*F45,H45*F45))) -> 0.009
I46: =IF(G46="","",IF(G46="g","per kg",IF(G46="ml","per L",IF(G46="oz","per lb",IF(G46="kg","per kg",IF(G46="L","per L",IF(G46="lb","per lb",IF(G46="fl oz","per fl oz","per unit")))))))) | J46: =IF(F46="","",IF(OR(G46="g",G46="ml"),H46/1000*F46,IF(G46="oz",H46/16*F46,H46*F46)))
I47: =IF(G47="","",IF(G47="g","per kg",IF(G47="ml","per L",IF(G47="oz","per lb",IF(G47="kg","per kg",IF(G47="L","per L",IF(G47="lb","per lb",IF(G47="fl oz","per fl oz","per unit")))))))) | J47: =IF(F47="","",IF(OR(G47="g",G47="ml"),H47/1000*F47,IF(G47="oz",H47/16*F47,H47*F47)))
I48: =IF(G48="","",IF(G48="g","per kg",IF(G48="ml","per L",IF(G48="oz","per lb",IF(G48="kg","per kg",IF(G48="L","per L",IF(G48="lb","per lb",IF(G48="fl oz","per fl oz","per unit")))))))) | J48: =IF(F48="","",IF(OR(G48="g",G48="ml"),H48/1000*F48,IF(G48="oz",H48/16*F48,H48*F48)))
I49: =IF(G49="","",IF(G49="g","per kg",IF(G49="ml","per L",IF(G49="oz","per lb",IF(G49="kg","per kg",IF(G49="L","per L",IF(G49="lb","per lb",IF(G49="fl oz","per fl oz","per unit")))))))) | J49: =IF(F49="","",IF(OR(G49="g",G49="ml"),H49/1000*F49,IF(G49="oz",H49/16*F49,H49*F49)))
I50: =IF(G50="","",IF(G50="g","per kg",IF(G50="ml","per L",IF(G50="oz","per lb",IF(G50="kg","per kg",IF(G50="L","per L",IF(G50="lb","per lb",IF(G50="fl oz","per fl oz","per unit")))))))) | J50: =IF(F50="","",IF(OR(G50="g",G50="ml"),H50/1000*F50,IF(G50="oz",H50/16*F50,H50*F50)))
E52: Total Ingredient Cost | J52: =SUM(J39:J50) -> 3.084
E53: Food Cost % | J53: =IFERROR(J52/F36,0) -> 0.20373091
E54: Gross Margin | J54: =F36-J52 -> 12.053615
E55: Gross Margin % | J55: =IFERROR(J54/F36,0) -> 0.79626909
E56: Biggest Cost Driver | J56: =IFERROR(INDEX(E39:E50,MATCH(MAX(J39:J50),J39:J50,0)),"-") -> Mozzarella
E57: Target Food Cost % | J57: =Dashboard!F7 -> 0.3
E58: DISH 3
E59: Dish Name | F59: Dish 3
E60: Selling Price (incl. VAT) | F60: 0
E61: VAT Rate % | F61: 0.09
E62: Price excl. VAT | F62: =IFERROR(F60/(1+F61),0) -> 0
E64: Ingredient | F64: Qty | G64: Unit | H64: ="Cost / Bulk ("&$F$3&")" -> Cost / Bulk (CHF) | I64: Bulk Unit | J64: ="Cost / Portion ("&$F$3&")" -> Cost / Portion (CHF)
I65: =IF(G65="","",IF(G65="g","per kg",IF(G65="ml","per L",IF(G65="oz","per lb",IF(G65="kg","per kg",IF(G65="L","per L",IF(G65="lb","per lb",IF(G65="fl oz","per fl oz","per unit")))))))) | J65: =IF(F65="","",IF(OR(G65="g",G65="ml"),H65/1000*F65,IF(G65="oz",H65/16*F65,H65*F65)))
I66: =IF(G66="","",IF(G66="g","per kg",IF(G66="ml","per L",IF(G66="oz","per lb",IF(G66="kg","per kg",IF(G66="L","per L",IF(G66="lb","per lb",IF(G66="fl oz","per fl oz","per unit")))))))) | J66: =IF(F66="","",IF(OR(G66="g",G66="ml"),H66/1000*F66,IF(G66="oz",H66/16*F66,H66*F66)))
I67: =IF(G67="","",IF(G67="g","per kg",IF(G67="ml","per L",IF(G67="oz","per lb",IF(G67="kg","per kg",IF(G67="L","per L",IF(G67="lb","per lb",IF(G67="fl oz","per fl oz","per unit")))))))) | J67: =IF(F67="","",IF(OR(G67="g",G67="ml"),H67/1000*F67,IF(G67="oz",H67/16*F67,H67*F67)))
I68: =IF(G68="","",IF(G68="g","per kg",IF(G68="ml","per L",IF(G68="oz","per lb",IF(G68="kg","per kg",IF(G68="L","per L",IF(G68="lb","per lb",IF(G68="fl oz","per fl oz","per unit")))))))) | J68: =IF(F68="","",IF(OR(G68="g",G68="ml"),H68/1000*F68,IF(G68="oz",H68/16*F68,H68*F68)))
I69: =IF(G69="","",IF(G69="g","per kg",IF(G69="ml","per L",IF(G69="oz","per lb",IF(G69="kg","per kg",IF(G69="L","per L",IF(G69="lb","per lb",IF(G69="fl oz","per fl oz","per unit")))))))) | J69: =IF(F69="","",IF(OR(G69="g",G69="ml"),H69/1000*F69,IF(G69="oz",H69/16*F69,H69*F69)))
I70: =IF(G70="","",IF(G70="g","per kg",IF(G70="ml","per L",IF(G70="oz","per lb",IF(G70="kg","per kg",IF(G70="L","per L",IF(G70="lb","per lb",IF(G70="fl oz","per fl oz","per unit")))))))) | J70: =IF(F70="","",IF(OR(G70="g",G70="ml"),H70/1000*F70,IF(G70="oz",H70/16*F70,H70*F70)))
I71: =IF(G71="","",IF(G71="g","per kg",IF(G71="ml","per L",IF(G71="oz","per lb",IF(G71="kg","per kg",IF(G71="L","per L",IF(G71="lb","per lb",IF(G71="fl oz","per fl oz","per unit")))))))) | J71: =IF(F71="","",IF(OR(G71="g",G71="ml"),H71/1000*F71,IF(G71="oz",H71/16*F71,H71*F71)))
I72: =IF(G72="","",IF(G72="g","per kg",IF(G72="ml","per L",IF(G72="oz","per lb",IF(G72="kg","per kg",IF(G72="L","per L",IF(G72="lb","per lb",IF(G72="fl oz","per fl oz","per unit")))))))) | J72: =IF(F72="","",IF(OR(G72="g",G72="ml"),H72/1000*F72,IF(G72="oz",H72/16*F72,H72*F72)))
I73: =IF(G73="","",IF(G73="g","per kg",IF(G73="ml","per L",IF(G73="oz","per lb",IF(G73="kg","per kg",IF(G73="L","per L",IF(G73="lb","per lb",IF(G73="fl oz","per fl oz","per unit")))))))) | J73: =IF(F73="","",IF(OR(G73="g",G73="ml"),H73/1000*F73,IF(G73="oz",H73/16*F73,H73*F73)))
I74: =IF(G74="","",IF(G74="g","per kg",IF(G74="ml","per L",IF(G74="oz","per lb",IF(G74="kg","per kg",IF(G74="L","per L",IF(G74="lb","per lb",IF(G74="fl oz","per fl oz","per unit")))))))) | J74: =IF(F74="","",IF(OR(G74="g",G74="ml"),H74/1000*F74,IF(G74="oz",H74/16*F74,H74*F74)))
I75: =IF(G75="","",IF(G75="g","per kg",IF(G75="ml","per L",IF(G75="oz","per lb",IF(G75="kg","per kg",IF(G75="L","per L",IF(G75="lb","per lb",IF(G75="fl oz","per fl oz","per unit")))))))) | J75: =IF(F75="","",IF(OR(G75="g",G75="ml"),H75/1000*F75,IF(G75="oz",H75/16*F75,H75*F75)))
I76: =IF(G76="","",IF(G76="g","per kg",IF(G76="ml","per L",IF(G76="oz","per lb",IF(G76="kg","per kg",IF(G76="L","per L",IF(G76="lb","per lb",IF(G76="fl oz","per fl oz","per unit")))))))) | J76: =IF(F76="","",IF(OR(G76="g",G76="ml"),H76/1000*F76,IF(G76="oz",H76/16*F76,H76*F76)))
E78: Total Ingredient Cost | J78: =SUM(J65:J76) -> 0
E79: Food Cost % | J79: =IFERROR(J78/F62,0) -> 0
E80: Gross Margin | J80: =F62-J78 -> 0
E81: Gross Margin % | J81: =IFERROR(J80/F62,0) -> 0
E82: Biggest Cost Driver | J82: =IFERROR(INDEX(E65:E76,MATCH(MAX(J65:J76),J65:J76,0)),"-") -> -
E83: Target Food Cost % | J83: =Dashboard!F7 -> 0.3
E84: DISH 4
E85: Dish Name | F85: Dish 4
E86: Selling Price (incl. VAT) | F86: 0
E87: VAT Rate % | F87: 0.09
E88: Price excl. VAT | F88: =IFERROR(F86/(1+F87),0) -> 0
E90: Ingredient | F90: Qty | G90: Unit | H90: ="Cost / Bulk ("&$F$3&")" -> Cost / Bulk (CHF) | I90: Bulk Unit | J90: ="Cost / Portion ("&$F$3&")" -> Cost / Portion (CHF)
I91: =IF(G91="","",IF(G91="g","per kg",IF(G91="ml","per L",IF(G91="oz","per lb",IF(G91="kg","per kg",IF(G91="L","per L",IF(G91="lb","per lb",IF(G91="fl oz","per fl oz","per unit")))))))) | J91: =IF(F91="","",IF(OR(G91="g",G91="ml"),H91/1000*F91,IF(G91="oz",H91/16*F91,H91*F91)))
I92: =IF(G92="","",IF(G92="g","per kg",IF(G92="ml","per L",IF(G92="oz","per lb",IF(G92="kg","per kg",IF(G92="L","per L",IF(G92="lb","per lb",IF(G92="fl oz","per fl oz","per unit")))))))) | J92: =IF(F92="","",IF(OR(G92="g",G92="ml"),H92/1000*F92,IF(G92="oz",H92/16*F92,H92*F92)))
I93: =IF(G93="","",IF(G93="g","per kg",IF(G93="ml","per L",IF(G93="oz","per lb",IF(G93="kg","per kg",IF(G93="L","per L",IF(G93="lb","per lb",IF(G93="fl oz","per fl oz","per unit")))))))) | J93: =IF(F93="","",IF(OR(G93="g",G93="ml"),H93/1000*F93,IF(G93="oz",H93/16*F93,H93*F93)))
I94: =IF(G94="","",IF(G94="g","per kg",IF(G94="ml","per L",IF(G94="oz","per lb",IF(G94="kg","per kg",IF(G94="L","per L",IF(G94="lb","per lb",IF(G94="fl oz","per fl oz","per unit")))))))) | J94: =IF(F94="","",IF(OR(G94="g",G94="ml"),H94/1000*F94,IF(G94="oz",H94/16*F94,H94*F94)))
I95: =IF(G95="","",IF(G95="g","per kg",IF(G95="ml","per L",IF(G95="oz","per lb",IF(G95="kg","per kg",IF(G95="L","per L",IF(G95="lb","per lb",IF(G95="fl oz","per fl oz","per unit")))))))) | J95: =IF(F95="","",IF(OR(G95="g",G95="ml"),H95/1000*F95,IF(G95="oz",H95/16*F95,H95*F95)))
I96: =IF(G96="","",IF(G96="g","per kg",IF(G96="ml","per L",IF(G96="oz","per lb",IF(G96="kg","per kg",IF(G96="L","per L",IF(G96="lb","per lb",IF(G96="fl oz","per fl oz","per unit")))))))) | J96: =IF(F96="","",IF(OR(G96="g",G96="ml"),H96/1000*F96,IF(G96="oz",H96/16*F96,H96*F96)))
I97: =IF(G97="","",IF(G97="g","per kg",IF(G97="ml","per L",IF(G97="oz","per lb",IF(G97="kg","per kg",IF(G97="L","per L",IF(G97="lb","per lb",IF(G97="fl oz","per fl oz","per unit")))))))) | J97: =IF(F97="","",IF(OR(G97="g",G97="ml"),H97/1000*F97,IF(G97="oz",H97/16*F97,H97*F97)))
I98: =IF(G98="","",IF(G98="g","per kg",IF(G98="ml","per L",IF(G98="oz","per lb",IF(G98="kg","per kg",IF(G98="L","per L",IF(G98="lb","per lb",IF(G98="fl oz","per fl oz","per unit")))))))) | J98: =IF(F98="","",IF(OR(G98="g",G98="ml"),H98/1000*F98,IF(G98="oz",H98/16*F98,H98*F98)))
I99: =IF(G99="","",IF(G99="g","per kg",IF(G99="ml","per L",IF(G99="oz","per lb",IF(G99="kg","per kg",IF(G99="L","per L",IF(G99="lb","per lb",IF(G99="fl oz","per fl oz","per unit")))))))) | J99: =IF(F99="","",IF(OR(G99="g",G99="ml"),H99/1000*F99,IF(G99="oz",H99/16*F99,H99*F99)))
I100: =IF(G100="","",IF(G100="g","per kg",IF(G100="ml","per L",IF(G100="oz","per lb",IF(G100="kg","per kg",IF(G100="L","per L",IF(G100="lb","per lb",IF(G100="fl oz","per fl oz","per unit")))))))) | J100: =IF(F100="","",IF(OR(G100="g",G100="ml"),H100/1000*F100,IF(G100="oz",H100/16*F100,H100*F100)))
I101: =IF(G101="","",IF(G101="g","per kg",IF(G101="ml","per L",IF(G101="oz","per lb",IF(G101="kg","per kg",IF(G101="L","per L",IF(G101="lb","per lb",IF(G101="fl oz","per fl oz","per unit")))))))) | J101: =IF(F101="","",IF(OR(G101="g",G101="ml"),H101/1000*F101,IF(G101="oz",H101/16*F101,H101*F101)))
I102: =IF(G102="","",IF(G102="g","per kg",IF(G102="ml","per L",IF(G102="oz","per lb",IF(G102="kg","per kg",IF(G102="L","per L",IF(G102="lb","per lb",IF(G102="fl oz","per fl oz","per unit")))))))) | J102: =IF(F102="","",IF(OR(G102="g",G102="ml"),H102/1000*F102,IF(G102="oz",H102/16*F102,H102*F102)))
E104: Total Ingredient Cost | J104: =SUM(J91:J102) -> 0
E105: Food Cost % | J105: =IFERROR(J104/F88,0) -> 0
E106: Gross Margin | J106: =F88-J104 -> 0
E107: Gross Margin % | J107: =IFERROR(J106/F88,0) -> 0
E108: Biggest Cost Driver | J108: =IFERROR(INDEX(E91:E102,MATCH(MAX(J91:J102),J91:J102,0)),"-") -> -
...

Sheet Notes
E1: NOTES
B2: Dish Profitability Tracker | E2: Reference guide and contact information
B3: 📊 Dashboard
B4: 🍽️ Dish Input | E4: WHAT IS FOOD COST %?
B5: 📝 Notes | E5: Food Cost % measures the proportion of a dish's selling price (excl. VAT) that goes toward ingredient costs.
E6: Formula: Food Cost % = Total Ingredient Cost ÷ Dish Price excl. VAT
E7: A lower food cost % means higher profitability per dish. Industry benchmarks typically range from 25% to 35%.
E9: HOW TO USE THIS TRACKER
E10: 1. Set your Target Food Cost % on the Dashboard sheet (default: 30%).
E11: 2. Go to the Dish Input sheet and enter your dish name and selling price (incl. VAT) for each dish.
E12: 3. Enter each ingredient: name, quantity, unit (g / ml / pcs), and cost per unit.
E13: 4. All calculations are automatic, food cost %, gross margin, and the biggest cost driver update instantly.
E14: 5. Return to the Dashboard to see all dishes compared side-by-side with status indicators.
E15: 6. Green = on target, Amber = within 5 percentage points above target, Red = more than 5pp above target.
E16: 7. The donut chart shows the average food cost % vs gross margin % across all active dishes.
E17: 8. The pie chart shows the ingredient-level breakdown of Dish 1 as a proportion of the selling price.
E19: IMPORTANT
... E26: Book a Clarity Call
